serialgrapher/__init__.py
serialgrapher-0.1.0.dist-info/LICENSE
serialgrapher-0.1.0.dist-info/METADATA
serialgrapher-0.1.0.dist-info/WHEEL
serialgrapher-0.1.0.dist-info/entry_points.txt
serialgrapher-0.1.0.dist-info/top_level.txt
serialgrapher-0.1.0.dist-info/RECORD
