Metadata-Version: 2.1
Name: serialgrapher
Version: 0.1.0
Summary: Utility for graphing CSV data received over a serial port
Home-page: https://github.com/jackw01/serial-grapher
Author: jackw01
License: MIT
Platform: UNKNOWN
Classifier: License :: OSI Approved :: MIT License
Classifier: Programming Language :: Python
Classifier: Programming Language :: Python :: 3
Classifier: Programming Language :: Python :: Implementation :: CPython
Classifier: Programming Language :: Python :: Implementation :: PyPy
Requires-Python: >=3.7.0
Requires-Dist: pyserial (>=3.4)
Requires-Dist: matplotlib (>=3.2.2)
